codes/01_combinacionales/01_lut/lut2.v
// Author: Guadalupe Alonso
// Name: lut2.v
//
// Description: Second option of Look Up Table

module lut2(
  input A,
  input B,
  input C,
  input D,
  output F
);

  wire c1;
  wire c2;
  wire c3;

  assign c1 = ~A & ~B &  D;
  assign c2 =  B & ~C & ~D;
  assign c3 = ~A &  C & ~D;
  assign  F = c1 | c2 | c3;

endmodule

codes/01_combinacionales/01_lut/lut1.v
// Author: Guadalupe Alonso
// Name: lut1.v
//
// Description: First option of Look Up Table

module lut1(
  input A,
  input B,
  input C,
  input D,
  output F
);

  assign F = (~A & ~B & D) | (B & ~C & ~D) | (~A & C & ~D);

endmodule

codes/01_combinacionales/01_lut/lut3.v
// Author: Guadalupe Alonso
// Name: lut3.v
//
// Description: Third option of Look Up Table

module lut3(
  input A,
  input B,
  input C,
  input D,
  output X
);

  and(c1,~A, B,~C);
  and(c2, A, B,~C);
  and(c3, B,~C, D);
  or(X,c1,c2,c3);

endmodule

codes/lut_tb.v
// Author: Guadalupe Alonso Contreras
// Name: lut1_tb.v
// Description: Testbench estimulos combinacionales.

`timescale 1ns / 100 ps
`include "lut1.v"
`include "lut2.v"
`include "lut3.v"

module lut_tb();
  // Definición de señales de entrada y salida
  reg A;
  reg B;
  reg C;
  reg D;

  wire X;

  // Instanciacion del modulo
  //lut1 dut(.A(A), .B(B), .C(C), .D(D), .X(X));
  //lut2 dut(.A(A), .B(B), .C(C), .D(D), .X(X));
  lut3 dut(.A(A), .B(B), .C(C), .D(D), .X(X));

  // Variables para archivo y ciclo for
  integer write_data;
  integer i;

  initial begin
    // Configuracion de archivos de salida
    write_data = $fopen("lut_tb_output.txt","w");
    $dumpfile("lut_tb.vcd");   //guarda lo que compila
    $dumpvars(0,lut_tb);     //selecciona variable que salen

    //b - binario, 4 - 4 bits, 0 - asigna ceros a los 4 bits
    //{A,B,C,D} = 4'd0; #20;   
    //{A,B,C,D} = 4'd1; #20;
    //{A,B,C,D} = 4'd2; #20;
    //{A,B,C,D} = 4'd3; #20;
    //{A,B,C,D} = 4'd4; #20;
    //{A,B,C,D} = 4'd5; #20;
    //{A,B,C,D} = 4'd6; #20;
    //{A,B,C,D} = 4'd7; #20;
    //{A,B,C,D} = 4'd8; #20;
    //{A,B,C,D} = 4'd9; #20;
    //{A,B,C,D} = 4'd10; #20;
    //{A,B,C,D} = 4'd11; #20;
    //{A,B,C,D} = 4'd12; #20;
    //{A,B,C,D} = 4'd13; #20;
    //{A,B,C,D} = 4'd14; #20;
    //{A,B,C,D} = 4'd15; #20;

    for (i = 0; i < 16; i++) begin
        {A,B,C,D} = i; #20;
        $fdisplay(write_data,"Entradas = %b, X = %7b", i, X);
    end

    $fclose(write_data);
    // A = 0; B = 0; C = 0; D = 0;
    // #20;

    $display("Test completed");
  end

endmodule;

codes/lut_tb.vcd
$date
	Fri Jun 30 11:08:58 2023
$end
$version
	Icarus Verilog
$end
$timescale
	100ps
$end
$scope module lut_tb $end
$var wire 1 ! X $end
$var reg 1 " A $end
$var reg 1 # B $end
$var reg 1 $ C $end
$var reg 1 % D $end
$var integer 32 & i [31:0] $end
$var integer 32 ' write_data [31:0] $end
$scope module dut $end
$var wire 1 " A $end
$var wire 1 # B $end
$var wire 1 $ C $end
$var wire 1 % D $end
$var reg 1 ! X $end
$upscope $end
$upscope $end
$enddefinitions $end
$comment Show the parameter values. $end
$dumpall
$end
#0
$dumpvars
b10000000000000000000000000000011 '
b0 &
0%
0$
0#
0"
0!
$end
#200
1%
b1 &
#400
1$
0%
b10 &
#600
1%
b11 &
#800
1#
0$
0%
b100 &
#1000
1%
b101 &
#1200
1$
0%
b110 &
#1400
1%
b111 &
#1600
1!
1"
0#
0$
0%
b1000 &
#1800
0!
1%
b1001 &
#2000
1$
0%
b1010 &
#2200
1%
b1011 &
#2400
1#
0$
0%
b1100 &
#2600
1!
1%
b1101 &
#2800
1$
0%
b1110 &
#3000
1%
b1111 &
#3200
b10000 &
